[
  {
    "name": "TDSB",
    "description": "The TDSB has received funding from the Ministry of Education to develop Community-Connected Experiential Learning (CCEL) projects within our Elementary and Secondary schools (Grades 5-12) in the 2021-22 academic year.",
    "buttonLink": "https://www.tdsb.on.ca/",
    "tier": "elite"
  },
  {
    "name": "Northern Secondary School",
    "buttonLink": "https://schoolweb.tdsb.on.ca/northernss/",
    "tier": "elite"
  },
  {
    "name": "Deloitte Digital",
    "buttonLink": "https://www.deloittedigital.com/us/en.html",
    "border": "0px",
    "tier": "silver"
  },
  {
    "name": "Onyen",
    "description": "It is a pleasure to assist young women especially to achieve academic success in STEM activities",
    "buttonLink": "https://www.onyen.com/#/home",
    "tier": "silver"
  },
  {
    "name": "Stones Throw Design",
    "buttonLink": "https://stonesthrowdesigninc.com/",
    "tier": "silver"
  },
  {
    "name": "Northern School Council",
    "buttonLink": "https://www.nsscouncil.com/",
    "tier": "silver"
  },
  {
    "name": "Northern Secondary School Foundation",
    "buttonLink": "https://www.nssf.ca/",
    "tier": "silver"
  },
  {
    "name": "Northern Student Affairs Council",
    "buttonLink": "https://www.northernsac.ca/",
    "tier": "silver"
  },
  {
    "name": "Parents & Students",
    "buttonVisible": "false",
    "tier": "bronze"
  }
]
